USBtingoGUI/__init__.py
USBtingoGUI/__main__.py
USBtingoGUI/resources.py
USBtingoGUI-1.0.dist-info/LICENSE
USBtingoGUI-1.0.dist-info/METADATA
USBtingoGUI-1.0.dist-info/WHEEL
USBtingoGUI-1.0.dist-info/entry_points.txt
USBtingoGUI-1.0.dist-info/top_level.txt
USBtingoGUI-1.0.dist-info/RECORD
