Metadata-Version: 2.1
Name: USBtingoGUI
Version: 1.0
Summary: USBtingoGUI is a graphical tool for sending and receiving CAN(-FD) messages using USBtingo.
Home-page: https://github.com/EmbedME/USBtingoGUI
Author: Thomas Fischl
Author-email: tfischl@gmx.de
License: UNKNOWN
Platform: UNKNOWN
Classifier: Programming Language :: Python :: 3
Classifier: License :: OSI Approved :: GNU General Public License v3 (GPLv3)
Classifier: Operating System :: OS Independent
License-File: LICENSE
Requires-Dist: PySide6
Requires-Dist: python-can-usbtingo
